inception_active_user/__init__.py
inception_active_user/settings_usr.py
inception_active_user/user.py
inception_active_user-0.1.5.dist-info/LICENSE
inception_active_user-0.1.5.dist-info/METADATA
inception_active_user-0.1.5.dist-info/WHEEL
inception_active_user-0.1.5.dist-info/top_level.txt
inception_active_user-0.1.5.dist-info/RECORD
