Metadata-Version: 2.1
Name: inception_active_user
Version: 0.1.5
Summary: inception_active_user is a package that allows you to get the active user
Home-page: https://github.com/KhaduaBloom/inceptionforcepackages/tree/main/PythonPackage/inceptionActiveUser
Author: KhaduaBloom
Author-email: khaduabloom@gmail.com
Classifier: Programming Language :: Python :: 3
Classifier: License :: OSI Approved :: MIT License
Classifier: Operating System :: OS Independent
Requires-Python: >=3.13.0
License-File: LICENSE
Requires-Dist: graypy==2.1.0
Requires-Dist: psutil==6.1.0
Requires-Dist: uvicorn
Requires-Dist: fastapi
Requires-Dist: pydantic-settings
Requires-Dist: aiohttp[speedups]
